InstagramGraphQL/__init__.py
InstagramGraphQL/constants.py
InstagramGraphQL/exceptions.py
InstagramGraphQL/hashtag.py
InstagramGraphQL/igql.py
InstagramGraphQL/location.py
InstagramGraphQL/media.py
InstagramGraphQL/user.py
InstagramGraphQL/utils.py
InstagramGraphQL-1.0.11.dist-info/LICENSE
InstagramGraphQL-1.0.11.dist-info/METADATA
InstagramGraphQL-1.0.11.dist-info/WHEEL
InstagramGraphQL-1.0.11.dist-info/top_level.txt
InstagramGraphQL-1.0.11.dist-info/RECORD
