Metadata-Version: 2.1
Name: InstagramGraphQL
Version: 1.0.11
Summary: InstagramGraphQL Unoffical API
Home-page: https://github.com/technerium/InstagramGraphQL
Author: Technerium
Author-email: technerium@gmail.com
License: MIT
Platform: UNKNOWN
Classifier: Programming Language :: Python :: 3
Classifier: License :: OSI Approved :: MIT License
Classifier: Operating System :: OS Independent
Requires-Dist: SmoothAPI
